learned_optimization/__init__.py
learned_optimization/checkpoints.py
learned_optimization/distributed.py
learned_optimization/distributed_test.py
learned_optimization/eval_training.py
learned_optimization/eval_training_test.py
learned_optimization/filesystem.py
learned_optimization/outer_train.py
learned_optimization/outer_train_test.py
learned_optimization/profile.py
learned_optimization/setup_experiment.py
learned_optimization/summary.py
learned_optimization/summary_test.py
learned_optimization/training.py
learned_optimization/tree_utils.py
learned_optimization/baselines/__init__.py
learned_optimization/baselines/hparam_sets.py
learned_optimization/baselines/run_archive.py
learned_optimization/baselines/run_trainer.py
learned_optimization/baselines/run_trainer_test.py
learned_optimization/baselines/utils.py
learned_optimization/continuous_eval/__init__.py
learned_optimization/continuous_eval/run_eval_chief.py
learned_optimization/continuous_eval/run_eval_chief_test.py
learned_optimization/continuous_eval/run_eval_worker.py
learned_optimization/continuous_eval/run_eval_worker_test.py
learned_optimization/continuous_eval/task_group_server.py
learned_optimization/continuous_eval/task_group_server_test.py
learned_optimization/learned_optimizers/__init__.py
learned_optimization/learned_optimizers/adafac_mlp_lopt.py
learned_optimization/learned_optimizers/adafac_mlp_lopt_test.py
learned_optimization/learned_optimizers/base.py
learned_optimization/learned_optimizers/base_test.py
learned_optimization/learned_optimizers/common.py
learned_optimization/learned_optimizers/mlp_lopt.py
learned_optimization/learned_optimizers/mlp_lopt_test.py
learned_optimization/learned_optimizers/nn_adam.py
learned_optimization/learned_optimizers/nn_adam_test.py
learned_optimization/learned_optimizers/rnn_mlp_lopt.py
learned_optimization/learned_optimizers/rnn_mlp_lopt_test.py
learned_optimization/learned_optimizers/test_utils.py
learned_optimization/optimizers/__init__.py
learned_optimization-0.0.1.dist-info/LICENSE
learned_optimization-0.0.1.dist-info/METADATA
learned_optimization-0.0.1.dist-info/WHEEL
learned_optimization-0.0.1.dist-info/top_level.txt
learned_optimization-0.0.1.dist-info/RECORD
